README.rst
setup.cfg
setup.py
PyHole.egg-info/PKG-INFO
PyHole.egg-info/SOURCES.txt
PyHole.egg-info/dependency_links.txt
PyHole.egg-info/top_level.txt
pyhole/__init__.py
pyhole/jsoned.py
pyhole/pyhole.py
pyhole/yamled.py
test/__init__.py
test/httptestserver.py
test/test_methods.py
test/test_pyhole.py
test/test_pyholejsoned.py
test/test_pyholeyamled.py