Metadata-Version: 1.1
Name: PyHole
Version: 1.6
Summary: Simple generic REST API client.
Home-page: http://packages.python.org/pyhole
Author: Krzysztof Dorosz
Author-email: cypreess@gmail.com
License: LGPL
Keywords: REST api connect connector client pyhole
Platform: UNKNOWN
Classifier: Topic :: Utilities
Classifier: Topic :: Internet :: WWW/HTTP
Classifier: License :: OSI Approved :: GNU Library or Lesser General Public License (LGPL)
Requires: pyyaml
